amk/kakashi/__init__.py
amk/kakashi/arg_parse.py
amk/kakashi/consts.py
amk/kakashi/kakashi.py
amk/kakashi/logger.py
amk.kakashi-1.0.0.dist-info/LICENSE
amk.kakashi-1.0.0.dist-info/METADATA
amk.kakashi-1.0.0.dist-info/WHEEL
amk.kakashi-1.0.0.dist-info/entry_points.txt
amk.kakashi-1.0.0.dist-info/top_level.txt
amk.kakashi-1.0.0.dist-info/RECORD
