Metadata-Version: 2.1
Name: amk.kakashi
Version: 1.0.0
Summary: 在保留原文件/目录结构的同时，批量替换指定文本，以快速创建文件分身
Home-page: https://github.com/AndyM129/FileDoppelganger
Author: Andy Meng
Author-email: andy_m129@163.com
License: GNU General Public License v3.0
Platform: UNKNOWN
Requires-Python: >=3.9
License-File: LICENSE
Requires-Dist: colorama
